[
{
    "about":"",
    "identifier":"group.restaurant.strega-waterfront.1marinaparkdrive.all",
    "deletedEntity":"",
    "lastUpdated":"2013-12-05 00:17:54 +0000",
    "name":"all",
    "restaurantIdentifier":"restaurant.strega-waterfront.1marinaparkdrive",
    "version":1,
    "wineUnitIdentifiers":"wineunit.restaurant.strega-waterfront.1marinaparkdrive.wine.brand.stemmari.varietal.pinotgrigio.2011.glass/wineunit.restaurant.strega-waterfront.1marinaparkdrive.wine.brand.marcofelluga.varietal.pinotgrigio.2011.glass/wineunit.restaurant.strega-waterfront.1marinaparkdrive.wine.brand.raymondlot3.varietal.chardonnay.2011.glass/wineunit.restaurant.strega-waterfront.1marinaparkdrive.wine.brand.rodneystrong.varietal.chardonnay.2011.glass/wineunit.restaurant.strega-waterfront.1marinaparkdrive.wine.brand.closduval.varietal.chardonnay.2011.glass/wineunit.restaurant.strega-waterfront.1marinaparkdrive.wine.brand.sonomacutrer.varietal.chardonnay.2011.glass/wineunit.restaurant.strega-waterfront.1marinaparkdrive.wine.brand.heitz.varietal.chardonnay.2010.glass/wineunit.restaurant.strega-waterfront.1marinaparkdrive.wine.brand.caymusconundrum..2011.glass/wineunit.restaurant.strega-waterfront.1marinaparkdrive.wine.brand.mauritsondrycreekvalley.varietal.sauvignonblanc.2001.glass/wineunit.restaurant.strega-waterfront.1marinaparkdrive.wine.brand.kimcrawford.varietal.sauvignonblanc.2012.glass/wineunit.restaurant.strega-waterfront.1marinaparkdrive.wine.brand.fournierlesbellesvignes.varietal.sancere.2011.glass/wineunit.restaurant.strega-waterfront.1marinaparkdrive.wine.brand.trimbachreserve.varietal.pinotgris.2008.glass/wineunit.restaurant.strega-waterfront.1marinaparkdrive.wine.brand.franciscoppola..2011.glass/wineunit.restaurant.strega-waterfront.1marinaparkdrive.wine.brand.s.a.prumessence.varietal.riesling.2012.glass/wineunit.restaurant.strega-waterfront.1marinaparkdrive.wine.brand.williamhillestate.varietal.cabernetsauvignon.2010.glass/wineunit.restaurant.strega-waterfront.1marinaparkdrive.wine.brand.steeleshootingstar.varietal.cabernetsauvignon.2010.glass/wineunit.restaurant.strega-waterfront.1marinaparkdrive.wine.brand.hessallomivineyard.varietal.cabernetsauvignon.2010.glass/wineunit.restaurant.strega-waterfront.1marinaparkdrive.wine.brand.st.francis.varietal.cabernetsauvignon.2009.glass/wineunit.restaurant.strega-waterfront.1marinaparkdrive.wine.brand.sequoiagrove.varietal.cabernetsauvignon.2009.glass/wineunit.restaurant.strega-waterfront.1marinaparkdrive.wine.brand.silveroak.varietal.cabernetsauvignon.2008.glass/wineunit.restaurant.strega-waterfront.1marinaparkdrive.wine.brand.alexandresirechlebordeaux.varietal.bordeaux.2009.glass/wineunit.restaurant.strega-waterfront.1marinaparkdrive.wine.brand.newtonclaret.varietal.meritage.2009.glass/wineunit.restaurant.strega-waterfront.1marinaparkdrive.wine.brand.banfisuperiore.varietal.chianti.2011.glass/wineunit.restaurant.strega-waterfront.1marinaparkdrive.wine.brand.classicobadiacoltibuono.varietal.chianti.2010.glass/wineunit.restaurant.strega-waterfront.1marinaparkdrive.wine.brand.classicoantinoripeppoli.varietal.chianti.2009.glass/wineunit.restaurant.strega-waterfront.1marinaparkdrive.wine.brand.caparzo.varietal.sangiovese.2010.glass/wineunit.restaurant.strega-waterfront.1marinaparkdrive.wine.brand.banficentine.varietal.supertuscan.2010.glass/wineunit.restaurant.strega-waterfront.1marinaparkdrive.wine.brand.lucente.varietal.supertuscan.2010.glass/wineunit.restaurant.strega-waterfront.1marinaparkdrive.wine.brand.damilanolecinquevigne.varietal.barolo.2009.glass/wineunit.restaurant.strega-waterfront.1marinaparkdrive.wine.brand.cooperhill.varietal.pinotnoir.2011.glass/wineunit.restaurant.strega-waterfront.1marinaparkdrive.wine.brand.talbottkalihart.varietal.pinotnoir.2010.glass/wineunit.restaurant.strega-waterfront.1marinaparkdrive.wine.brand.rodneystrongestate.varietal.pinotnoir.2011.glass/wineunit.restaurant.strega-waterfront.1marinaparkdrive.wine.brand.etudelyric.varietal.pinotnoir.2011.glass/wineunit.restaurant.strega-waterfront.1marinaparkdrive.wine.brand.spellbound.varietal.merlot.2009.glass/wineunit.restaurant.strega-waterfront.1marinaparkdrive.wine.brand.pauldolan.varietal.zinfandel.2010.glass/wineunit.restaurant.strega-waterfront.1marinaparkdrive.wine.brand.alamos.varietal.malbec.2011.glass/wineunit.restaurant.strega-waterfront.1marinaparkdrive.wine.brand.benziger.varietal.syrah.2007.glass/wineunit.restaurant.strega-waterfront.1marinaparkdrive.wine.brand.penfoldskoonungahills.varietal.shiraz.2010.glass",
    "restaurant":"",
    "wineUnits":[
  {
    "flightIdentifiers":"",
    "groupIdentifiers":"",
    "identifier":"wineunit.restaurant.strega-waterfront.1marinaparkdrive.wine.brand.stemmari.varietal.pinotgrigio.2011.glass",
    "deletedEntity":"",
    "lastUpdated":"2013-12-05 00:17:54 +0000",
    "price":8,
    "quantity":"glass",
    "restaurantIdentifier":"restaurant.strega-waterfront.1marinaparkdrive",
    "version":1,
    "wineIdentifier":"wine.brand.stemmari.varietal.pinotgrigio.2011",
    "flights":"",
    "groups":"",
    "wine":[{
    "alcoholPercentage":4.4,
    "brandIdentifier":"brand.stemmari",
    "color":"white",
    "country":"italy",
    "dessert":"0",
    "identifier":"wine.brand.stemmari.varietal.pinotgrigio.2011",
    "deletedEntity":"",
    "lastUpdated":"2013-12-05 00:17:54 +0000",
    "name":"",
    "region":"sicily",
    "sparkling":"0",
    "state":"",
    "tastingNoteIdentifiers":"tastingnote.lemon/tastingnote.minerals",
    "varietalIdentifiers":"varietal.pinotgrigio",
    "version":1,
    "vineyard":"sicily",
    "vintage":2011,
    "wineUnitIdentifiers":"wineunit.restaurant.strega-waterfront.1marinaparkdrive.wine.brand.stemmari.varietal.pinotgrigio.2011.glass",
    "brand":[{
    "about":"",
    "identifier":"brand.stemmari",
    "deletedEntity":"",
    "lastUpdated":"2013-12-05 00:17:54 +0000",
    "name":"stemmari",
    "version":1,
    "website":"",
    "wineIdentifiers":"",
    "wines":""
  }],
    "tastingNotes":"",
    "varietals":"",
    "wineUnits":""
  }]
  },
  {
    "flightIdentifiers":"",
    "groupIdentifiers":"",
    "identifier":"wineunit.restaurant.strega-waterfront.1marinaparkdrive.wine.brand.marcofelluga.varietal.pinotgrigio.2011.glass",
    "deletedEntity":"",
    "lastUpdated":"2013-12-05 00:17:54 +0000",
    "price":11,
    "quantity":"glass",
    "restaurantIdentifier":"restaurant.strega-waterfront.1marinaparkdrive",
    "version":1,
    "wineIdentifier":"wine.brand.marcofelluga.varietal.pinotgrigio.2011",
    "flights":"",
    "groups":"",
    "wine":[{
    "alcoholPercentage":3.5,
    "brandIdentifier":"brand.marcofelluga",
    "color":"white",
    "country":"italy",
    "dessert":"0",
    "identifier":"wine.brand.marcofelluga.varietal.pinotgrigio.2011",
    "deletedEntity":"",
    "lastUpdated":"2013-12-05 00:17:54 +0000",
    "name":"",
    "region":"friuli",
    "sparkling":"0",
    "state":"",
    "tastingNoteIdentifiers":"tastingnote.apple/tastingnote.pear",
    "varietalIdentifiers":"varietal.pinotgrigio",
    "version":1,
    "vineyard":"friuli",
    "vintage":2011,
    "wineUnitIdentifiers":"wineunit.restaurant.strega-waterfront.1marinaparkdrive.wine.brand.marcofelluga.varietal.pinotgrigio.2011.glass",
    "brand":[{
    "about":"",
    "identifier":"brand.marcofelluga",
    "deletedEntity":"",
    "lastUpdated":"2013-12-05 00:17:54 +0000",
    "name":"marco felluga",
    "version":1,
    "website":"",
    "wineIdentifiers":"",
    "wines":""
  }],
    "tastingNotes":"",
    "varietals":"",
    "wineUnits":""
  }]
  },
  {
    "flightIdentifiers":"",
    "groupIdentifiers":"",
    "identifier":"wineunit.restaurant.strega-waterfront.1marinaparkdrive.wine.brand.raymondlot3.varietal.chardonnay.2011.glass",
    "deletedEntity":"",
    "lastUpdated":"2013-12-05 00:17:54 +0000",
    "price":8,
    "quantity":"glass",
    "restaurantIdentifier":"restaurant.strega-waterfront.1marinaparkdrive",
    "version":1,
    "wineIdentifier":"wine.brand.raymondlot3.varietal.chardonnay.2011",
    "flights":"",
    "groups":"",
    "wine":[{
    "alcoholPercentage":4.2,
    "brandIdentifier":"brand.raymondlot3",
    "color":"white",
    "country":"united states of america",
    "dessert":"0",
    "identifier":"wine.brand.raymondlot3.varietal.chardonnay.2011",
    "deletedEntity":"",
    "lastUpdated":"2013-12-05 00:17:54 +0000",
    "name":"",
    "region":"",
    "sparkling":"0",
    "state":"california",
    "tastingNoteIdentifiers":"tastingnote.beeswax",
    "varietalIdentifiers":"varietal.chardonnay",
    "version":1,
    "vineyard":"central coast",
    "vintage":2011,
    "wineUnitIdentifiers":"wineunit.restaurant.strega-waterfront.1marinaparkdrive.wine.brand.raymondlot3.varietal.chardonnay.2011.glass",
    "brand":[{
    "about":"",
    "identifier":"brand.raymondlot3",
    "deletedEntity":"",
    "lastUpdated":"2013-12-05 00:17:54 +0000",
    "name":"raymond lot 3",
    "version":1,
    "website":"",
    "wineIdentifiers":"",
    "wines":""
  }],
    "tastingNotes":"",
    "varietals":"",
    "wineUnits":""
  }]
  },
  {
    "flightIdentifiers":"",
    "groupIdentifiers":"",
    "identifier":"wineunit.restaurant.strega-waterfront.1marinaparkdrive.wine.brand.rodneystrong.varietal.chardonnay.2011.glass",
    "deletedEntity":"",
    "lastUpdated":"2013-12-05 00:17:54 +0000",
    "price":10,
    "quantity":"glass",
    "restaurantIdentifier":"restaurant.strega-waterfront.1marinaparkdrive",
    "version":1,
    "wineIdentifier":"wine.brand.rodneystrong.varietal.chardonnay.2011",
    "flights":"",
    "groups":"",
    "wine":[{
    "alcoholPercentage":3.8,
    "brandIdentifier":"brand.rodneystrong",
    "color":"white",
    "country":"united states of america",
    "dessert":"0",
    "identifier":"wine.brand.rodneystrong.varietal.chardonnay.2011",
    "deletedEntity":"",
    "lastUpdated":"2013-12-05 00:17:54 +0000",
    "name":"",
    "region":"",
    "sparkling":"0",
    "state":"california",
    "tastingNoteIdentifiers":"tastingnote.bellpepper",
    "varietalIdentifiers":"varietal.chardonnay",
    "version":1,
    "vineyard":"sonoma",
    "vintage":2011,
    "wineUnitIdentifiers":"wineunit.restaurant.strega-waterfront.1marinaparkdrive.wine.brand.rodneystrong.varietal.chardonnay.2011.glass",
    "brand":[{
    "about":"",
    "identifier":"brand.rodneystrong",
    "deletedEntity":"",
    "lastUpdated":"2013-12-05 00:17:54 +0000",
    "name":"rodney strong",
    "version":1,
    "website":"",
    "wineIdentifiers":"",
    "wines":""
  }],
    "tastingNotes":"",
    "varietals":"",
    "wineUnits":""
  }]
  },
  {
    "flightIdentifiers":"",
    "groupIdentifiers":"",
    "identifier":"wineunit.restaurant.strega-waterfront.1marinaparkdrive.wine.brand.closduval.varietal.chardonnay.2011.glass",
    "deletedEntity":"",
    "lastUpdated":"2013-12-05 00:17:54 +0000",
    "price":12,
    "quantity":"glass",
    "restaurantIdentifier":"restaurant.strega-waterfront.1marinaparkdrive",
    "version":1,
    "wineIdentifier":"wine.brand.closduval.varietal.chardonnay.2011",
    "flights":"",
    "groups":"",
    "wine":[{
    "alcoholPercentage":3.2,
    "brandIdentifier":"brand.closduval",
    "color":"white",
    "country":"united states of america",
    "dessert":"0",
    "identifier":"wine.brand.closduval.varietal.chardonnay.2011",
    "deletedEntity":"",
    "lastUpdated":"2013-12-05 00:17:54 +0000",
    "name":"",
    "region":"",
    "sparkling":"0",
    "state":"california",
    "tastingNoteIdentifiers":"tastingnote.blackberry",
    "varietalIdentifiers":"varietal.chardonnay",
    "version":1,
    "vineyard":"napa",
    "vintage":2011,
    "wineUnitIdentifiers":"wineunit.restaurant.strega-waterfront.1marinaparkdrive.wine.brand.closduval.varietal.chardonnay.2011.glass",
    "brand":[{
    "about":"",
    "identifier":"brand.closduval",
    "deletedEntity":"",
    "lastUpdated":"2013-12-05 00:17:54 +0000",
    "name":"clos du val",
    "version":1,
    "website":"",
    "wineIdentifiers":"",
    "wines":""
  }],
    "tastingNotes":"",
    "varietals":"",
    "wineUnits":""
  }]
  },
  {
    "flightIdentifiers":"",
    "groupIdentifiers":"",
    "identifier":"wineunit.restaurant.strega-waterfront.1marinaparkdrive.wine.brand.sonomacutrer.varietal.chardonnay.2011.glass",
    "deletedEntity":"",
    "lastUpdated":"2013-12-05 00:17:54 +0000",
    "price":15,
    "quantity":"glass",
    "restaurantIdentifier":"restaurant.strega-waterfront.1marinaparkdrive",
    "version":1,
    "wineIdentifier":"wine.brand.sonomacutrer.varietal.chardonnay.2011",
    "flights":"",
    "groups":"",
    "wine":[{
    "alcoholPercentage":4.1,
    "brandIdentifier":"brand.sonomacutrer",
    "color":"white",
    "country":"united states of america",
    "dessert":"0",
    "identifier":"wine.brand.sonomacutrer.varietal.chardonnay.2011",
    "deletedEntity":"",
    "lastUpdated":"2013-12-05 00:17:54 +0000",
    "name":"",
    "region":"",
    "sparkling":"0",
    "state":"california",
    "tastingNoteIdentifiers":"tastingnote.blackcherry",
    "varietalIdentifiers":"varietal.chardonnay",
    "version":1,
    "vineyard":"russian river",
    "vintage":2011,
    "wineUnitIdentifiers":"wineunit.restaurant.strega-waterfront.1marinaparkdrive.wine.brand.sonomacutrer.varietal.chardonnay.2011.glass",
    "brand":[{
    "about":"",
    "identifier":"brand.sonomacutrer",
    "deletedEntity":"",
    "lastUpdated":"2013-12-05 00:17:54 +0000",
    "name":"sonoma cutrer",
    "version":1,
    "website":"",
    "wineIdentifiers":"",
    "wines":""
  }],
    "tastingNotes":"",
    "varietals":"",
    "wineUnits":""
  }]
  },
  {
    "flightIdentifiers":"",
    "groupIdentifiers":"",
    "identifier":"wineunit.restaurant.strega-waterfront.1marinaparkdrive.wine.brand.heitz.varietal.chardonnay.2010.glass",
    "deletedEntity":"",
    "lastUpdated":"2013-12-05 00:17:54 +0000",
    "price":17,
    "quantity":"glass",
    "restaurantIdentifier":"restaurant.strega-waterfront.1marinaparkdrive",
    "version":1,
    "wineIdentifier":"wine.brand.heitz.varietal.chardonnay.2010",
    "flights":"",
    "groups":"",
    "wine":[{
    "alcoholPercentage":4.4,
    "brandIdentifier":"brand.heitz",
    "color":"white",
    "country":"united states of america",
    "dessert":"0",
    "identifier":"wine.brand.heitz.varietal.chardonnay.2010",
    "deletedEntity":"",
    "lastUpdated":"2013-12-05 00:17:54 +0000",
    "name":"",
    "region":"",
    "sparkling":"0",
    "state":"california",
    "tastingNoteIdentifiers":"tastingnote.blackcurrants",
    "varietalIdentifiers":"varietal.chardonnay",
    "version":1,
    "vineyard":"napa",
    "vintage":2010,
    "wineUnitIdentifiers":"wineunit.restaurant.strega-waterfront.1marinaparkdrive.wine.brand.heitz.varietal.chardonnay.2010.glass",
    "brand":[{
    "about":"",
    "identifier":"brand.heitz",
    "deletedEntity":"",
    "lastUpdated":"2013-12-05 00:17:54 +0000",
    "name":"heitz",
    "version":1,
    "website":"",
    "wineIdentifiers":"",
    "wines":""
  }],
    "tastingNotes":"",
    "varietals":"",
    "wineUnits":""
  }]
  },
  {
    "flightIdentifiers":"",
    "groupIdentifiers":"",
    "identifier":"wineunit.restaurant.strega-waterfront.1marinaparkdrive.wine.brand.caymusconundrum..2011.glass",
    "deletedEntity":"",
    "lastUpdated":"2013-12-05 00:17:54 +0000",
    "price":14,
    "quantity":"glass",
    "restaurantIdentifier":"restaurant.strega-waterfront.1marinaparkdrive",
    "version":1,
    "wineIdentifier":"wine.brand.caymusconundrum..2011",
    "flights":"",
    "groups":"",
    "wine":[{
    "alcoholPercentage":3.7,
    "brandIdentifier":"brand.caymusconundrum",
    "color":"white",
    "country":"united states of america",
    "dessert":"0",
    "identifier":"wine.brand.caymusconundrum..2011",
    "deletedEntity":"",
    "lastUpdated":"2013-12-05 00:17:54 +0000",
    "name":"",
    "region":"",
    "sparkling":"0",
    "state":"california",
    "tastingNoteIdentifiers":"tastingnote.blackpepper",
    "varietalIdentifiers":"",
    "version":1,
    "vineyard":"napa",
    "vintage":2011,
    "wineUnitIdentifiers":"wineunit.restaurant.strega-waterfront.1marinaparkdrive.wine.brand.caymusconundrum..2011.glass",
    "brand":[{
    "about":"",
    "identifier":"brand.caymusconundrum",
    "deletedEntity":"",
    "lastUpdated":"2013-12-05 00:17:54 +0000",
    "name":"caymus conundrum",
    "version":1,
    "website":"",
    "wineIdentifiers":"",
    "wines":""
  }],
    "tastingNotes":"",
    "varietals":"",
    "wineUnits":""
  }]
  },
  {
    "flightIdentifiers":"",
    "groupIdentifiers":"",
    "identifier":"wineunit.restaurant.strega-waterfront.1marinaparkdrive.wine.brand.mauritsondrycreekvalley.varietal.sauvignonblanc.2001.glass",
    "deletedEntity":"",
    "lastUpdated":"2013-12-05 00:17:54 +0000",
    "price":9,
    "quantity":"glass",
    "restaurantIdentifier":"restaurant.strega-waterfront.1marinaparkdrive",
    "version":1,
    "wineIdentifier":"wine.brand.mauritsondrycreekvalley.varietal.sauvignonblanc.2001",
    "flights":"",
    "groups":"",
    "wine":[{
    "alcoholPercentage":3.6,
    "brandIdentifier":"brand.mauritsondrycreekvalley",
    "color":"white",
    "country":"united states of america",
    "dessert":"0",
    "identifier":"wine.brand.mauritsondrycreekvalley.varietal.sauvignonblanc.2001",
    "deletedEntity":"",
    "lastUpdated":"2013-12-05 00:17:54 +0000",
    "name":"",
    "region":"",
    "sparkling":"0",
    "state":"californa",
    "tastingNoteIdentifiers":"tastingnote.butter",
    "varietalIdentifiers":"varietal.sauvignonblanc",
    "version":1,
    "vineyard":"sonoma",
    "vintage":2001,
    "wineUnitIdentifiers":"wineunit.restaurant.strega-waterfront.1marinaparkdrive.wine.brand.mauritsondrycreekvalley.varietal.sauvignonblanc.2001.glass",
    "brand":[{
    "about":"",
    "identifier":"brand.mauritsondrycreekvalley",
    "deletedEntity":"",
    "lastUpdated":"2013-12-05 00:17:54 +0000",
    "name":"mauritson dry creek valley",
    "version":1,
    "website":"",
    "wineIdentifiers":"",
    "wines":""
  }],
    "tastingNotes":"",
    "varietals":"",
    "wineUnits":""
  }]
  },
  {
    "flightIdentifiers":"",
    "groupIdentifiers":"",
    "identifier":"wineunit.restaurant.strega-waterfront.1marinaparkdrive.wine.brand.kimcrawford.varietal.sauvignonblanc.2012.glass",
    "deletedEntity":"",
    "lastUpdated":"2013-12-05 00:17:54 +0000",
    "price":12,
    "quantity":"glass",
    "restaurantIdentifier":"restaurant.strega-waterfront.1marinaparkdrive",
    "version":1,
    "wineIdentifier":"wine.brand.kimcrawford.varietal.sauvignonblanc.2012",
    "flights":"",
    "groups":"",
    "wine":[{
    "alcoholPercentage":3.9,
    "brandIdentifier":"brand.kimcrawford",
    "color":"white",
    "country":"new zealand",
    "dessert":"0",
    "identifier":"wine.brand.kimcrawford.varietal.sauvignonblanc.2012",
    "deletedEntity":"",
    "lastUpdated":"2013-12-05 00:17:54 +0000",
    "name":"",
    "region":"marlborough",
    "sparkling":"0",
    "state":"",
    "tastingNoteIdentifiers":"tastingnote.capsicum",
    "varietalIdentifiers":"varietal.sauvignonblanc",
    "version":1,
    "vineyard":"marlborough",
    "vintage":2012,
    "wineUnitIdentifiers":"wineunit.restaurant.strega-waterfront.1marinaparkdrive.wine.brand.kimcrawford.varietal.sauvignonblanc.2012.glass",
    "brand":[{
    "about":"",
    "identifier":"brand.kimcrawford",
    "deletedEntity":"",
    "lastUpdated":"2013-12-05 00:17:54 +0000",
    "name":"kim crawford",
    "version":1,
    "website":"",
    "wineIdentifiers":"",
    "wines":""
  }],
    "tastingNotes":"",
    "varietals":"",
    "wineUnits":""
  }]
  },
  {
    "flightIdentifiers":"",
    "groupIdentifiers":"",
    "identifier":"wineunit.restaurant.strega-waterfront.1marinaparkdrive.wine.brand.fournierlesbellesvignes.varietal.sancere.2011.glass",
    "deletedEntity":"",
    "lastUpdated":"2013-12-05 00:17:54 +0000",
    "price":13,
    "quantity":"glass",
    "restaurantIdentifier":"restaurant.strega-waterfront.1marinaparkdrive",
    "version":1,
    "wineIdentifier":"wine.brand.fournierlesbellesvignes.varietal.sancere.2011",
    "flights":"",
    "groups":"",
    "wine":[{
    "alcoholPercentage":4.4,
    "brandIdentifier":"brand.fournierlesbellesvignes",
    "color":"white",
    "country":"france",
    "dessert":"0",
    "identifier":"wine.brand.fournierlesbellesvignes.varietal.sancere.2011",
    "deletedEntity":"",
    "lastUpdated":"2013-12-05 00:17:54 +0000",
    "name":"",
    "region":"loire",
    "sparkling":"0",
    "state":"",
    "tastingNoteIdentifiers":"tastingnote.chocolate",
    "varietalIdentifiers":"varietal.sancere",
    "version":1,
    "vineyard":"loire valley",
    "vintage":2011,
    "wineUnitIdentifiers":"wineunit.restaurant.strega-waterfront.1marinaparkdrive.wine.brand.fournierlesbellesvignes.varietal.sancere.2011.glass",
    "brand":[{
    "about":"",
    "identifier":"brand.fournierlesbellesvignes",
    "deletedEntity":"",
    "lastUpdated":"2013-12-05 00:17:54 +0000",
    "name":"fournier les belles vignes",
    "version":1,
    "website":"",
    "wineIdentifiers":"",
    "wines":""
  }],
    "tastingNotes":"",
    "varietals":"",
    "wineUnits":""
  }]
  },
  {
    "flightIdentifiers":"",
    "groupIdentifiers":"",
    "identifier":"wineunit.restaurant.strega-waterfront.1marinaparkdrive.wine.brand.trimbachreserve.varietal.pinotgris.2008.glass",
    "deletedEntity":"",
    "lastUpdated":"2013-12-05 00:17:54 +0000",
    "price":9,
    "quantity":"glass",
    "restaurantIdentifier":"restaurant.strega-waterfront.1marinaparkdrive",
    "version":1,
    "wineIdentifier":"wine.brand.trimbachreserve.varietal.pinotgris.2008",
    "flights":"",
    "groups":"",
    "wine":[{
    "alcoholPercentage":3.5,
    "brandIdentifier":"brand.trimbachreserve",
    "color":"white",
    "country":"france",
    "dessert":"0",
    "identifier":"wine.brand.trimbachreserve.varietal.pinotgris.2008",
    "deletedEntity":"",
    "lastUpdated":"2013-12-05 00:17:54 +0000",
    "name":"",
    "region":"alsace",
    "sparkling":"0",
    "state":"",
    "tastingNoteIdentifiers":"tastingnote.cinnamon",
    "varietalIdentifiers":"varietal.pinotgris",
    "version":1,
    "vineyard":"alsace",
    "vintage":2008,
    "wineUnitIdentifiers":"wineunit.restaurant.strega-waterfront.1marinaparkdrive.wine.brand.trimbachreserve.varietal.pinotgris.2008.glass",
    "brand":[{
    "about":"",
    "identifier":"brand.trimbachreserve",
    "deletedEntity":"",
    "lastUpdated":"2013-12-05 00:17:54 +0000",
    "name":"trimbach reserve",
    "version":1,
    "website":"",
    "wineIdentifiers":"",
    "wines":""
  }],
    "tastingNotes":"",
    "varietals":"",
    "wineUnits":""
  }]
  },
  {
    "flightIdentifiers":"",
    "groupIdentifiers":"",
    "identifier":"wineunit.restaurant.strega-waterfront.1marinaparkdrive.wine.brand.franciscoppola..2011.glass",
    "deletedEntity":"",
    "lastUpdated":"2013-12-05 00:17:54 +0000",
    "price":9,
    "quantity":"glass",
    "restaurantIdentifier":"restaurant.strega-waterfront.1marinaparkdrive",
    "version":1,
    "wineIdentifier":"wine.brand.franciscoppola..2011",
    "flights":"",
    "groups":"",
    "wine":[{
    "alcoholPercentage":4.2,
    "brandIdentifier":"brand.franciscoppola",
    "color":"rose",
    "country":"united states of america",
    "dessert":"0",
    "identifier":"wine.brand.franciscoppola..2011",
    "deletedEntity":"",
    "lastUpdated":"2013-12-05 00:17:54 +0000",
    "name":"francis coppola sofia",
    "region":"",
    "sparkling":"0",
    "state":"california",
    "tastingNoteIdentifiers":"tastingnote.citrus",
    "varietalIdentifiers":"",
    "version":1,
    "vineyard":"monterey county",
    "vintage":2011,
    "wineUnitIdentifiers":"wineunit.restaurant.strega-waterfront.1marinaparkdrive.wine.brand.franciscoppola..2011.glass",
    "brand":[{
    "about":"",
    "identifier":"brand.franciscoppola",
    "deletedEntity":"",
    "lastUpdated":"2013-12-05 00:17:54 +0000",
    "name":"francis coppola",
    "version":1,
    "website":"",
    "wineIdentifiers":"",
    "wines":""
  }],
    "tastingNotes":"",
    "varietals":"",
    "wineUnits":""
  }]
  },
  {
    "flightIdentifiers":"",
    "groupIdentifiers":"",
    "identifier":"wineunit.restaurant.strega-waterfront.1marinaparkdrive.wine.brand.s.a.prumessence.varietal.riesling.2012.glass",
    "deletedEntity":"",
    "lastUpdated":"2013-12-05 00:17:54 +0000",
    "price":8,
    "quantity":"glass",
    "restaurantIdentifier":"restaurant.strega-waterfront.1marinaparkdrive",
    "version":1,
    "wineIdentifier":"wine.brand.s.a.prumessence.varietal.riesling.2012",
    "flights":"",
    "groups":"",
    "wine":[{
    "alcoholPercentage":3.8,
    "brandIdentifier":"brand.s.a.prumessence",
    "color":"white",
    "country":"germany",
    "dessert":"0",
    "identifier":"wine.brand.s.a.prumessence.varietal.riesling.2012",
    "deletedEntity":"",
    "lastUpdated":"2013-12-05 00:17:54 +0000",
    "name":"",
    "region":"mosel",
    "sparkling":"0",
    "state":"",
    "tastingNoteIdentifiers":"tastingnote.citrusfruits",
    "varietalIdentifiers":"varietal.riesling",
    "version":1,
    "vineyard":"mosel",
    "vintage":2012,
    "wineUnitIdentifiers":"wineunit.restaurant.strega-waterfront.1marinaparkdrive.wine.brand.s.a.prumessence.varietal.riesling.2012.glass",
    "brand":[{
    "about":"",
    "identifier":"brand.s.a.prumessence",
    "deletedEntity":"",
    "lastUpdated":"2013-12-05 00:17:54 +0000",
    "name":"s.a. prum essence",
    "version":1,
    "website":"",
    "wineIdentifiers":"",
    "wines":""
  }],
    "tastingNotes":"",
    "varietals":"",
    "wineUnits":""
  }]
  },
  {
    "flightIdentifiers":"",
    "groupIdentifiers":"",
    "identifier":"wineunit.restaurant.strega-waterfront.1marinaparkdrive.wine.brand.williamhillestate.varietal.cabernetsauvignon.2010.glass",
    "deletedEntity":"",
    "lastUpdated":"2013-12-05 00:17:54 +0000",
    "price":9,
    "quantity":"glass",
    "restaurantIdentifier":"restaurant.strega-waterfront.1marinaparkdrive",
    "version":1,
    "wineIdentifier":"wine.brand.williamhillestate.varietal.cabernetsauvignon.2010",
    "flights":"",
    "groups":"",
    "wine":[{
    "alcoholPercentage":3.2,
    "brandIdentifier":"brand.williamhillestate",
    "color":"red",
    "country":"united states of america",
    "dessert":"0",
    "identifier":"wine.brand.williamhillestate.varietal.cabernetsauvignon.2010",
    "deletedEntity":"",
    "lastUpdated":"2013-12-05 00:17:54 +0000",
    "name":"",
    "region":"",
    "sparkling":"0",
    "state":"california",
    "tastingNoteIdentifiers":"tastingnote.clove",
    "varietalIdentifiers":"varietal.cabernetsauvignon",
    "version":1,
    "vineyard":"central coast",
    "vintage":2010,
    "wineUnitIdentifiers":"wineunit.restaurant.strega-waterfront.1marinaparkdrive.wine.brand.williamhillestate.varietal.cabernetsauvignon.2010.glass",
    "brand":[{
    "about":"",
    "identifier":"brand.williamhillestate",
    "deletedEntity":"",
    "lastUpdated":"2013-12-05 00:17:54 +0000",
    "name":"william hill estate",
    "version":1,
    "website":"",
    "wineIdentifiers":"",
    "wines":""
  }],
    "tastingNotes":"",
    "varietals":"",
    "wineUnits":""
  }]
  },
  {
    "flightIdentifiers":"",
    "groupIdentifiers":"",
    "identifier":"wineunit.restaurant.strega-waterfront.1marinaparkdrive.wine.brand.steeleshootingstar.varietal.cabernetsauvignon.2010.glass",
    "deletedEntity":"",
    "lastUpdated":"2013-12-05 00:17:54 +0000",
    "price":10,
    "quantity":"glass",
    "restaurantIdentifier":"restaurant.strega-waterfront.1marinaparkdrive",
    "version":1,
    "wineIdentifier":"wine.brand.steeleshootingstar.varietal.cabernetsauvignon.2010",
    "flights":"",
    "groups":"",
    "wine":[{
    "alcoholPercentage":4.1,
    "brandIdentifier":"brand.steeleshootingstar",
    "color":"red",
    "country":"united states of america",
    "dessert":"0",
    "identifier":"wine.brand.steeleshootingstar.varietal.cabernetsauvignon.2010",
    "deletedEntity":"",
    "lastUpdated":"2013-12-05 00:17:54 +0000",
    "name":"",
    "region":"",
    "sparkling":"0",
    "state":"california",
    "tastingNoteIdentifiers":"tastingnote.cream",
    "varietalIdentifiers":"varietal.cabernetsauvignon",
    "version":1,
    "vineyard":"lake county",
    "vintage":2010,
    "wineUnitIdentifiers":"wineunit.restaurant.strega-waterfront.1marinaparkdrive.wine.brand.steeleshootingstar.varietal.cabernetsauvignon.2010.glass",
    "brand":[{
    "about":"",
    "identifier":"brand.steeleshootingstar",
    "deletedEntity":"",
    "lastUpdated":"2013-12-05 00:17:54 +0000",
    "name":"steele shooting star",
    "version":1,
    "website":"",
    "wineIdentifiers":"",
    "wines":""
  }],
    "tastingNotes":"",
    "varietals":"",
    "wineUnits":""
  }]
  },
  {
    "flightIdentifiers":"",
    "groupIdentifiers":"",
    "identifier":"wineunit.restaurant.strega-waterfront.1marinaparkdrive.wine.brand.hessallomivineyard.varietal.cabernetsauvignon.2010.glass",
    "deletedEntity":"",
    "lastUpdated":"2013-12-05 00:17:54 +0000",
    "price":12,
    "quantity":"glass",
    "restaurantIdentifier":"restaurant.strega-waterfront.1marinaparkdrive",
    "version":1,
    "wineIdentifier":"wine.brand.hessallomivineyard.varietal.cabernetsauvignon.2010",
    "flights":"",
    "groups":"",
    "wine":[{
    "alcoholPercentage":4.4,
    "brandIdentifier":"brand.hessallomivineyard",
    "color":"red",
    "country":"united states of america",
    "dessert":"0",
    "identifier":"wine.brand.hessallomivineyard.varietal.cabernetsauvignon.2010",
    "deletedEntity":"",
    "lastUpdated":"2013-12-05 00:17:54 +0000",
    "name":"",
    "region":"",
    "sparkling":"0",
    "state":"california",
    "tastingNoteIdentifiers":"tastingnote.cutgrass",
    "varietalIdentifiers":"varietal.cabernetsauvignon",
    "version":1,
    "vineyard":"napa",
    "vintage":2010,
    "wineUnitIdentifiers":"wineunit.restaurant.strega-waterfront.1marinaparkdrive.wine.brand.hessallomivineyard.varietal.cabernetsauvignon.2010.glass",
    "brand":[{
    "about":"",
    "identifier":"brand.hessallomivineyard",
    "deletedEntity":"",
    "lastUpdated":"2013-12-05 00:17:54 +0000",
    "name":"hess allomi vineyard",
    "version":1,
    "website":"",
    "wineIdentifiers":"",
    "wines":""
  }],
    "tastingNotes":"",
    "varietals":"",
    "wineUnits":""
  }]
  },
  {
    "flightIdentifiers":"",
    "groupIdentifiers":"",
    "identifier":"wineunit.restaurant.strega-waterfront.1marinaparkdrive.wine.brand.st.francis.varietal.cabernetsauvignon.2009.glass",
    "deletedEntity":"",
    "lastUpdated":"2013-12-05 00:17:54 +0000",
    "price":14,
    "quantity":"glass",
    "restaurantIdentifier":"restaurant.strega-waterfront.1marinaparkdrive",
    "version":1,
    "wineIdentifier":"wine.brand.st.francis.varietal.cabernetsauvignon.2009",
    "flights":"",
    "groups":"",
    "wine":[{
    "alcoholPercentage":3.7,
    "brandIdentifier":"brand.st.francis",
    "color":"red",
    "country":"united states of america",
    "dessert":"0",
    "identifier":"wine.brand.st.francis.varietal.cabernetsauvignon.2009",
    "deletedEntity":"",
    "lastUpdated":"2013-12-05 00:17:54 +0000",
    "name":"",
    "region":"",
    "sparkling":"0",
    "state":"california",
    "tastingNoteIdentifiers":"tastingnote.darkfruits",
    "varietalIdentifiers":"varietal.cabernetsauvignon",
    "version":1,
    "vineyard":"sonoma",
    "vintage":2009,
    "wineUnitIdentifiers":"wineunit.restaurant.strega-waterfront.1marinaparkdrive.wine.brand.st.francis.varietal.cabernetsauvignon.2009.glass",
    "brand":[{
    "about":"",
    "identifier":"brand.st.francis",
    "deletedEntity":"",
    "lastUpdated":"2013-12-05 00:17:54 +0000",
    "name":"st. francis",
    "version":1,
    "website":"",
    "wineIdentifiers":"",
    "wines":""
  }],
    "tastingNotes":"",
    "varietals":"",
    "wineUnits":""
  }]
  },
  {
    "flightIdentifiers":"",
    "groupIdentifiers":"",
    "identifier":"wineunit.restaurant.strega-waterfront.1marinaparkdrive.wine.brand.sequoiagrove.varietal.cabernetsauvignon.2009.glass",
    "deletedEntity":"",
    "lastUpdated":"2013-12-05 00:17:54 +0000",
    "price":19,
    "quantity":"glass",
    "restaurantIdentifier":"restaurant.strega-waterfront.1marinaparkdrive",
    "version":1,
    "wineIdentifier":"wine.brand.sequoiagrove.varietal.cabernetsauvignon.2009",
    "flights":"",
    "groups":"",
    "wine":[{
    "alcoholPercentage":3.6,
    "brandIdentifier":"brand.sequoiagrove",
    "color":"red",
    "country":"united states of america",
    "dessert":"0",
    "identifier":"wine.brand.sequoiagrove.varietal.cabernetsauvignon.2009",
    "deletedEntity":"",
    "lastUpdated":"2013-12-05 00:17:54 +0000",
    "name":"",
    "region":"",
    "sparkling":"0",
    "state":"california",
    "tastingNoteIdentifiers":"tastingnote.earthy",
    "varietalIdentifiers":"varietal.cabernetsauvignon",
    "version":1,
    "vineyard":"napa",
    "vintage":2009,
    "wineUnitIdentifiers":"wineunit.restaurant.strega-waterfront.1marinaparkdrive.wine.brand.sequoiagrove.varietal.cabernetsauvignon.2009.glass",
    "brand":[{
    "about":"",
    "identifier":"brand.sequoiagrove",
    "deletedEntity":"",
    "lastUpdated":"2013-12-05 00:17:54 +0000",
    "name":"sequoia grove",
    "version":1,
    "website":"",
    "wineIdentifiers":"",
    "wines":""
  }],
    "tastingNotes":"",
    "varietals":"",
    "wineUnits":""
  }]
  },
  {
    "flightIdentifiers":"",
    "groupIdentifiers":"",
    "identifier":"wineunit.restaurant.strega-waterfront.1marinaparkdrive.wine.brand.silveroak.varietal.cabernetsauvignon.2008.glass",
    "deletedEntity":"",
    "lastUpdated":"2013-12-05 00:17:54 +0000",
    "price":25,
    "quantity":"glass",
    "restaurantIdentifier":"restaurant.strega-waterfront.1marinaparkdrive",
    "version":1,
    "wineIdentifier":"wine.brand.silveroak.varietal.cabernetsauvignon.2008",
    "flights":"",
    "groups":"",
    "wine":[{
    "alcoholPercentage":3.9,
    "brandIdentifier":"brand.silveroak",
    "color":"red",
    "country":"united states of america",
    "dessert":"0",
    "identifier":"wine.brand.silveroak.varietal.cabernetsauvignon.2008",
    "deletedEntity":"",
    "lastUpdated":"2013-12-05 00:17:54 +0000",
    "name":"",
    "region":"",
    "sparkling":"0",
    "state":"california",
    "tastingNoteIdentifiers":"tastingnote.earthyminerality",
    "varietalIdentifiers":"varietal.cabernetsauvignon",
    "version":1,
    "vineyard":"alexander valley",
    "vintage":2008,
    "wineUnitIdentifiers":"wineunit.restaurant.strega-waterfront.1marinaparkdrive.wine.brand.silveroak.varietal.cabernetsauvignon.2008.glass",
    "brand":[{
    "about":"",
    "identifier":"brand.silveroak",
    "deletedEntity":"",
    "lastUpdated":"2013-12-05 00:17:54 +0000",
    "name":"silver oak",
    "version":1,
    "website":"",
    "wineIdentifiers":"",
    "wines":""
  }],
    "tastingNotes":"",
    "varietals":"",
    "wineUnits":""
  }]
  },
  {
    "flightIdentifiers":"",
    "groupIdentifiers":"",
    "identifier":"wineunit.restaurant.strega-waterfront.1marinaparkdrive.wine.brand.alexandresirechlebordeaux.varietal.bordeaux.2009.glass",
    "deletedEntity":"",
    "lastUpdated":"2013-12-05 00:17:54 +0000",
    "price":10,
    "quantity":"glass",
    "restaurantIdentifier":"restaurant.strega-waterfront.1marinaparkdrive",
    "version":1,
    "wineIdentifier":"wine.brand.alexandresirechlebordeaux.varietal.bordeaux.2009",
    "flights":"",
    "groups":"",
    "wine":[{
    "alcoholPercentage":4.4,
    "brandIdentifier":"brand.alexandresirechlebordeaux",
    "color":"red",
    "country":"france",
    "dessert":"0",
    "identifier":"wine.brand.alexandresirechlebordeaux.varietal.bordeaux.2009",
    "deletedEntity":"",
    "lastUpdated":"2013-12-05 00:17:54 +0000",
    "name":"",
    "region":"bordeaux",
    "sparkling":"0",
    "state":"",
    "tastingNoteIdentifiers":"tastingnote.elderberries",
    "varietalIdentifiers":"varietal.bordeaux",
    "version":1,
    "vineyard":"bordeaux",
    "vintage":2009,
    "wineUnitIdentifiers":"wineunit.restaurant.strega-waterfront.1marinaparkdrive.wine.brand.alexandresirechlebordeaux.varietal.bordeaux.2009.glass",
    "brand":[{
    "about":"",
    "identifier":"brand.alexandresirechlebordeaux",
    "deletedEntity":"",
    "lastUpdated":"2013-12-05 00:17:54 +0000",
    "name":"alexandre sirech le bordeaux",
    "version":1,
    "website":"",
    "wineIdentifiers":"",
    "wines":""
  }],
    "tastingNotes":"",
    "varietals":"",
    "wineUnits":""
  }]
  },
  {
    "flightIdentifiers":"",
    "groupIdentifiers":"",
    "identifier":"wineunit.restaurant.strega-waterfront.1marinaparkdrive.wine.brand.newtonclaret.varietal.meritage.2009.glass",
    "deletedEntity":"",
    "lastUpdated":"2013-12-05 00:17:54 +0000",
    "price":15,
    "quantity":"glass",
    "restaurantIdentifier":"restaurant.strega-waterfront.1marinaparkdrive",
    "version":1,
    "wineIdentifier":"wine.brand.newtonclaret.varietal.meritage.2009",
    "flights":"",
    "groups":"",
    "wine":[{
    "alcoholPercentage":3.5,
    "brandIdentifier":"brand.newtonclaret",
    "color":"red",
    "country":"united states of america",
    "dessert":"0",
    "identifier":"wine.brand.newtonclaret.varietal.meritage.2009",
    "deletedEntity":"",
    "lastUpdated":"2013-12-05 00:17:54 +0000",
    "name":"",
    "region":"",
    "sparkling":"0",
    "state":"california",
    "tastingNoteIdentifiers":"tastingnote.eucalyptus",
    "varietalIdentifiers":"varietal.meritage",
    "version":1,
    "vineyard":"napa",
    "vintage":2009,
    "wineUnitIdentifiers":"wineunit.restaurant.strega-waterfront.1marinaparkdrive.wine.brand.newtonclaret.varietal.meritage.2009.glass",
    "brand":[{
    "about":"",
    "identifier":"brand.newtonclaret",
    "deletedEntity":"",
    "lastUpdated":"2013-12-05 00:17:54 +0000",
    "name":"newton claret",
    "version":1,
    "website":"",
    "wineIdentifiers":"",
    "wines":""
  }],
    "tastingNotes":"",
    "varietals":"",
    "wineUnits":""
  }]
  },
  {
    "flightIdentifiers":"flight.restaurant.strega-waterfront.1marinaparkdrive.classicchiantis",
    "groupIdentifiers":"",
    "identifier":"wineunit.restaurant.strega-waterfront.1marinaparkdrive.wine.brand.banfisuperiore.varietal.chianti.2011.glass",
    "deletedEntity":"",
    "lastUpdated":"2013-12-05 00:17:54 +0000",
    "price":10,
    "quantity":"glass",
    "restaurantIdentifier":"restaurant.strega-waterfront.1marinaparkdrive",
    "version":1,
    "wineIdentifier":"wine.brand.banfisuperiore.varietal.chianti.2011",
    "flights":"",
    "groups":"",
    "wine":[{
    "alcoholPercentage":4.2,
    "brandIdentifier":"brand.banfisuperiore",
    "color":"red",
    "country":"italy",
    "dessert":"0",
    "identifier":"wine.brand.banfisuperiore.varietal.chianti.2011",
    "deletedEntity":"",
    "lastUpdated":"2013-12-05 00:17:54 +0000",
    "name":"",
    "region":"tuscany",
    "sparkling":"0",
    "state":"",
    "tastingNoteIdentifiers":"tastingnote.freshlymowngrass",
    "varietalIdentifiers":"varietal.chianti",
    "version":1,
    "vineyard":"tuscany",
    "vintage":2011,
    "wineUnitIdentifiers":"wineunit.restaurant.strega-waterfront.1marinaparkdrive.wine.brand.banfisuperiore.varietal.chianti.2011.glass",
    "brand":[{
    "about":"",
    "identifier":"brand.banfisuperiore",
    "deletedEntity":"",
    "lastUpdated":"2013-12-05 00:17:54 +0000",
    "name":"banfi superiore",
    "version":1,
    "website":"",
    "wineIdentifiers":"",
    "wines":""
  }],
    "tastingNotes":"",
    "varietals":"",
    "wineUnits":""
  }]
  },
  {
    "flightIdentifiers":"flight.restaurant.strega-waterfront.1marinaparkdrive.classicchiantis",
    "groupIdentifiers":"",
    "identifier":"wineunit.restaurant.strega-waterfront.1marinaparkdrive.wine.brand.classicobadiacoltibuono.varietal.chianti.2010.glass",
    "deletedEntity":"",
    "lastUpdated":"2013-12-05 00:17:54 +0000",
    "price":12,
    "quantity":"glass",
    "restaurantIdentifier":"restaurant.strega-waterfront.1marinaparkdrive",
    "version":1,
    "wineIdentifier":"wine.brand.classicobadiacoltibuono.varietal.chianti.2010",
    "flights":"",
    "groups":"",
    "wine":[{
    "alcoholPercentage":3.8,
    "brandIdentifier":"brand.classicobadiacoltibuono",
    "color":"red",
    "country":"italy",
    "dessert":"0",
    "identifier":"wine.brand.classicobadiacoltibuono.varietal.chianti.2010",
    "deletedEntity":"",
    "lastUpdated":"2013-12-05 00:17:54 +0000",
    "name":"",
    "region":"tuscany",
    "sparkling":"0",
    "state":"",
    "tastingNoteIdentifiers":"tastingnote.gooseberry",
    "varietalIdentifiers":"varietal.chianti",
    "version":1,
    "vineyard":"tuscany",
    "vintage":2010,
    "wineUnitIdentifiers":"wineunit.restaurant.strega-waterfront.1marinaparkdrive.wine.brand.classicobadiacoltibuono.varietal.chianti.2010.glass",
    "brand":[{
    "about":"",
    "identifier":"brand.classicobadiacoltibuono",
    "deletedEntity":"",
    "lastUpdated":"2013-12-05 00:17:54 +0000",
    "name":"classico badia coltibuono",
    "version":1,
    "website":"",
    "wineIdentifiers":"",
    "wines":""
  }],
    "tastingNotes":"",
    "varietals":"",
    "wineUnits":""
  }]
  },
  {
    "flightIdentifiers":"flight.restaurant.strega-waterfront.1marinaparkdrive.classicchiantis",
    "groupIdentifiers":"",
    "identifier":"wineunit.restaurant.strega-waterfront.1marinaparkdrive.wine.brand.classicoantinoripeppoli.varietal.chianti.2009.glass",
    "deletedEntity":"",
    "lastUpdated":"2013-12-05 00:17:54 +0000",
    "price":14,
    "quantity":"glass",
    "restaurantIdentifier":"restaurant.strega-waterfront.1marinaparkdrive",
    "version":1,
    "wineIdentifier":"wine.brand.classicoantinoripeppoli.varietal.chianti.2009",
    "flights":"",
    "groups":"",
    "wine":[{
    "alcoholPercentage":3.2,
    "brandIdentifier":"brand.classicoantinoripeppoli",
    "color":"red",
    "country":"italy",
    "dessert":"0",
    "identifier":"wine.brand.classicoantinoripeppoli.varietal.chianti.2009",
    "deletedEntity":"",
    "lastUpdated":"2013-12-05 00:17:54 +0000",
    "name":"",
    "region":"tuscany",
    "sparkling":"0",
    "state":"",
    "tastingNoteIdentifiers":"tastingnote.grapefruit",
    "varietalIdentifiers":"varietal.chianti",
    "version":1,
    "vineyard":"tuscany",
    "vintage":2009,
    "wineUnitIdentifiers":"wineunit.restaurant.strega-waterfront.1marinaparkdrive.wine.brand.classicoantinoripeppoli.varietal.chianti.2009.glass",
    "brand":[{
    "about":"",
    "identifier":"brand.classicoantinoripeppoli",
    "deletedEntity":"",
    "lastUpdated":"2013-12-05 00:17:54 +0000",
    "name":"classico antinori peppoli",
    "version":1,
    "website":"",
    "wineIdentifiers":"",
    "wines":""
  }],
    "tastingNotes":"",
    "varietals":"",
    "wineUnits":""
  }]
  },
  {
    "flightIdentifiers":"",
    "groupIdentifiers":"",
    "identifier":"wineunit.restaurant.strega-waterfront.1marinaparkdrive.wine.brand.caparzo.varietal.sangiovese.2010.glass",
    "deletedEntity":"",
    "lastUpdated":"2013-12-05 00:17:54 +0000",
    "price":7,
    "quantity":"glass",
    "restaurantIdentifier":"restaurant.strega-waterfront.1marinaparkdrive",
    "version":1,
    "wineIdentifier":"wine.brand.caparzo.varietal.sangiovese.2010",
    "flights":"",
    "groups":"",
    "wine":[{
    "alcoholPercentage":4.1,
    "brandIdentifier":"brand.caparzo",
    "color":"red",
    "country":"italy",
    "dessert":"0",
    "identifier":"wine.brand.caparzo.varietal.sangiovese.2010",
    "deletedEntity":"",
    "lastUpdated":"2013-12-05 00:17:54 +0000",
    "name":"",
    "region":"tuscany",
    "sparkling":"0",
    "state":"",
    "tastingNoteIdentifiers":"tastingnote.greenbellpepper",
    "varietalIdentifiers":"varietal.sangiovese",
    "version":1,
    "vineyard":"tuscany",
    "vintage":2010,
    "wineUnitIdentifiers":"wineunit.restaurant.strega-waterfront.1marinaparkdrive.wine.brand.caparzo.varietal.sangiovese.2010.glass",
    "brand":[{
    "about":"",
    "identifier":"brand.caparzo",
    "deletedEntity":"",
    "lastUpdated":"2013-12-05 00:17:54 +0000",
    "name":"caparzo",
    "version":1,
    "website":"",
    "wineIdentifiers":"",
    "wines":""
  }],
    "tastingNotes":"",
    "varietals":"",
    "wineUnits":""
  }]
  },
  {
    "flightIdentifiers":"",
    "groupIdentifiers":"",
    "identifier":"wineunit.restaurant.strega-waterfront.1marinaparkdrive.wine.brand.banficentine.varietal.supertuscan.2010.glass",
    "deletedEntity":"",
    "lastUpdated":"2013-12-05 00:17:54 +0000",
    "price":9,
    "quantity":"glass",
    "restaurantIdentifier":"restaurant.strega-waterfront.1marinaparkdrive",
    "version":1,
    "wineIdentifier":"wine.brand.banficentine.varietal.supertuscan.2010",
    "flights":"",
    "groups":"",
    "wine":[{
    "alcoholPercentage":4.4,
    "brandIdentifier":"brand.banficentine",
    "color":"red",
    "country":"italy",
    "dessert":"0",
    "identifier":"wine.brand.banficentine.varietal.supertuscan.2010",
    "deletedEntity":"",
    "lastUpdated":"2013-12-05 00:17:54 +0000",
    "name":"",
    "region":"tuscany",
    "sparkling":"0",
    "state":"",
    "tastingNoteIdentifiers":"tastingnote.greenfruits",
    "varietalIdentifiers":"varietal.supertuscan",
    "version":1,
    "vineyard":"tuscany",
    "vintage":2010,
    "wineUnitIdentifiers":"wineunit.restaurant.strega-waterfront.1marinaparkdrive.wine.brand.banficentine.varietal.supertuscan.2010.glass",
    "brand":[{
    "about":"",
    "identifier":"brand.banficentine",
    "deletedEntity":"",
    "lastUpdated":"2013-12-05 00:17:54 +0000",
    "name":"banfi centine",
    "version":1,
    "website":"",
    "wineIdentifiers":"",
    "wines":""
  }],
    "tastingNotes":"",
    "varietals":"",
    "wineUnits":""
  }]
  },
  {
    "flightIdentifiers":"",
    "groupIdentifiers":"",
    "identifier":"wineunit.restaurant.strega-waterfront.1marinaparkdrive.wine.brand.lucente.varietal.supertuscan.2010.glass",
    "deletedEntity":"",
    "lastUpdated":"2013-12-05 00:17:54 +0000",
    "price":17,
    "quantity":"glass",
    "restaurantIdentifier":"restaurant.strega-waterfront.1marinaparkdrive",
    "version":1,
    "wineIdentifier":"wine.brand.lucente.varietal.supertuscan.2010",
    "flights":"",
    "groups":"",
    "wine":[{
    "alcoholPercentage":3.7,
    "brandIdentifier":"brand.lucente",
    "color":"red",
    "country":"italy",
    "dessert":"0",
    "identifier":"wine.brand.lucente.varietal.supertuscan.2010",
    "deletedEntity":"",
    "lastUpdated":"2013-12-05 00:17:54 +0000",
    "name":"",
    "region":"tuscany",
    "sparkling":"0",
    "state":"",
    "tastingNoteIdentifiers":"tastingnote.guava",
    "varietalIdentifiers":"varietal.supertuscan",
    "version":1,
    "vineyard":"tuscany",
    "vintage":2010,
    "wineUnitIdentifiers":"wineunit.restaurant.strega-waterfront.1marinaparkdrive.wine.brand.lucente.varietal.supertuscan.2010.glass",
    "brand":[{
    "about":"",
    "identifier":"brand.lucente",
    "deletedEntity":"",
    "lastUpdated":"2013-12-05 00:17:54 +0000",
    "name":"lucente",
    "version":1,
    "website":"",
    "wineIdentifiers":"",
    "wines":""
  }],
    "tastingNotes":"",
    "varietals":"",
    "wineUnits":""
  }]
  },
  {
    "flightIdentifiers":"",
    "groupIdentifiers":"",
    "identifier":"wineunit.restaurant.strega-waterfront.1marinaparkdrive.wine.brand.damilanolecinquevigne.varietal.barolo.2009.glass",
    "deletedEntity":"",
    "lastUpdated":"2013-12-05 00:17:54 +0000",
    "price":19,
    "quantity":"glass",
    "restaurantIdentifier":"restaurant.strega-waterfront.1marinaparkdrive",
    "version":1,
    "wineIdentifier":"wine.brand.damilanolecinquevigne.varietal.barolo.2009",
    "flights":"",
    "groups":"",
    "wine":[{
    "alcoholPercentage":3.6,
    "brandIdentifier":"brand.damilanolecinquevigne",
    "color":"red",
    "country":"italy",
    "dessert":"0",
    "identifier":"wine.brand.damilanolecinquevigne.varietal.barolo.2009",
    "deletedEntity":"",
    "lastUpdated":"2013-12-05 00:17:54 +0000",
    "name":"",
    "region":"piedmont",
    "sparkling":"0",
    "state":"",
    "tastingNoteIdentifiers":"tastingnote.herbs",
    "varietalIdentifiers":"varietal.barolo",
    "version":1,
    "vineyard":"piedmont",
    "vintage":2009,
    "wineUnitIdentifiers":"wineunit.restaurant.strega-waterfront.1marinaparkdrive.wine.brand.damilanolecinquevigne.varietal.barolo.2009.glass",
    "brand":[{
    "about":"",
    "identifier":"brand.damilanolecinquevigne",
    "deletedEntity":"",
    "lastUpdated":"2013-12-05 00:17:54 +0000",
    "name":"damilano le cinque vigne",
    "version":1,
    "website":"",
    "wineIdentifiers":"",
    "wines":""
  }],
    "tastingNotes":"",
    "varietals":"",
    "wineUnits":""
  }]
  },
  {
    "flightIdentifiers":"",
    "groupIdentifiers":"",
    "identifier":"wineunit.restaurant.strega-waterfront.1marinaparkdrive.wine.brand.cooperhill.varietal.pinotnoir.2011.glass",
    "deletedEntity":"",
    "lastUpdated":"2013-12-05 00:17:54 +0000",
    "price":10,
    "quantity":"glass",
    "restaurantIdentifier":"restaurant.strega-waterfront.1marinaparkdrive",
    "version":1,
    "wineIdentifier":"wine.brand.cooperhill.varietal.pinotnoir.2011",
    "flights":"",
    "groups":"",
    "wine":[{
    "alcoholPercentage":3.9,
    "brandIdentifier":"brand.cooperhill",
    "color":"red",
    "country":"united states of america",
    "dessert":"0",
    "identifier":"wine.brand.cooperhill.varietal.pinotnoir.2011",
    "deletedEntity":"",
    "lastUpdated":"2013-12-05 00:17:54 +0000",
    "name":"",
    "region":"",
    "sparkling":"0",
    "state":"oregon",
    "tastingNoteIdentifiers":"tastingnote.honey",
    "varietalIdentifiers":"varietal.pinotnoir",
    "version":1,
    "vineyard":"willamette valley",
    "vintage":2011,
    "wineUnitIdentifiers":"wineunit.restaurant.strega-waterfront.1marinaparkdrive.wine.brand.cooperhill.varietal.pinotnoir.2011.glass",
    "brand":[{
    "about":"",
    "identifier":"brand.cooperhill",
    "deletedEntity":"",
    "lastUpdated":"2013-12-05 00:17:54 +0000",
    "name":"cooper hill",
    "version":1,
    "website":"",
    "wineIdentifiers":"",
    "wines":""
  }],
    "tastingNotes":"",
    "varietals":"",
    "wineUnits":""
  }]
  },
  {
    "flightIdentifiers":"",
    "groupIdentifiers":"",
    "identifier":"wineunit.restaurant.strega-waterfront.1marinaparkdrive.wine.brand.talbottkalihart.varietal.pinotnoir.2010.glass",
    "deletedEntity":"",
    "lastUpdated":"2013-12-05 00:17:54 +0000",
    "price":12,
    "quantity":"glass",
    "restaurantIdentifier":"restaurant.strega-waterfront.1marinaparkdrive",
    "version":1,
    "wineIdentifier":"wine.brand.talbottkalihart.varietal.pinotnoir.2010",
    "flights":"",
    "groups":"",
    "wine":[{
    "alcoholPercentage":4.4,
    "brandIdentifier":"brand.talbottkalihart",
    "color":"red",
    "country":"united states of america",
    "dessert":"0",
    "identifier":"wine.brand.talbottkalihart.varietal.pinotnoir.2010",
    "deletedEntity":"",
    "lastUpdated":"2013-12-05 00:17:54 +0000",
    "name":"",
    "region":"",
    "sparkling":"0",
    "state":"california",
    "tastingNoteIdentifiers":"tastingnote.leather",
    "varietalIdentifiers":"varietal.pinotnoir",
    "version":1,
    "vineyard":"monterey",
    "vintage":2010,
    "wineUnitIdentifiers":"wineunit.restaurant.strega-waterfront.1marinaparkdrive.wine.brand.talbottkalihart.varietal.pinotnoir.2010.glass",
    "brand":[{
    "about":"",
    "identifier":"brand.talbottkalihart",
    "deletedEntity":"",
    "lastUpdated":"2013-12-05 00:17:54 +0000",
    "name":"talbott kali hart",
    "version":1,
    "website":"",
    "wineIdentifiers":"",
    "wines":""
  }],
    "tastingNotes":"",
    "varietals":"",
    "wineUnits":""
  }]
  },
  {
    "flightIdentifiers":"",
    "groupIdentifiers":"",
    "identifier":"wineunit.restaurant.strega-waterfront.1marinaparkdrive.wine.brand.rodneystrongestate.varietal.pinotnoir.2011.glass",
    "deletedEntity":"",
    "lastUpdated":"2013-12-05 00:17:54 +0000",
    "price":13,
    "quantity":"glass",
    "restaurantIdentifier":"restaurant.strega-waterfront.1marinaparkdrive",
    "version":1,
    "wineIdentifier":"wine.brand.rodneystrongestate.varietal.pinotnoir.2011",
    "flights":"",
    "groups":"",
    "wine":[{
    "alcoholPercentage":3.5,
    "brandIdentifier":"brand.rodneystrongestate",
    "color":"red",
    "country":"united states of america",
    "dessert":"0",
    "identifier":"wine.brand.rodneystrongestate.varietal.pinotnoir.2011",
    "deletedEntity":"",
    "lastUpdated":"2013-12-05 00:17:54 +0000",
    "name":"",
    "region":"",
    "sparkling":"0",
    "state":"california",
    "tastingNoteIdentifiers":"tastingnote.lemon",
    "varietalIdentifiers":"varietal.pinotnoir",
    "version":1,
    "vineyard":"russian river",
    "vintage":2011,
    "wineUnitIdentifiers":"wineunit.restaurant.strega-waterfront.1marinaparkdrive.wine.brand.rodneystrongestate.varietal.pinotnoir.2011.glass",
    "brand":[{
    "about":"",
    "identifier":"brand.rodneystrongestate",
    "deletedEntity":"",
    "lastUpdated":"2013-12-05 00:17:54 +0000",
    "name":"rodney strong estate",
    "version":1,
    "website":"",
    "wineIdentifiers":"",
    "wines":""
  }],
    "tastingNotes":"",
    "varietals":"",
    "wineUnits":""
  }]
  },
  {
    "flightIdentifiers":"",
    "groupIdentifiers":"",
    "identifier":"wineunit.restaurant.strega-waterfront.1marinaparkdrive.wine.brand.etudelyric.varietal.pinotnoir.2011.glass",
    "deletedEntity":"",
    "lastUpdated":"2013-12-05 00:17:54 +0000",
    "price":15,
    "quantity":"glass",
    "restaurantIdentifier":"restaurant.strega-waterfront.1marinaparkdrive",
    "version":1,
    "wineIdentifier":"wine.brand.etudelyric.varietal.pinotnoir.2011",
    "flights":"",
    "groups":"",
    "wine":[{
    "alcoholPercentage":4.2,
    "brandIdentifier":"brand.etudelyric",
    "color":"red",
    "country":"united states of america",
    "dessert":"0",
    "identifier":"wine.brand.etudelyric.varietal.pinotnoir.2011",
    "deletedEntity":"",
    "lastUpdated":"2013-12-05 00:17:54 +0000",
    "name":"",
    "region":"",
    "sparkling":"0",
    "state":"california",
    "tastingNoteIdentifiers":"tastingnote.lime",
    "varietalIdentifiers":"varietal.pinotnoir",
    "version":1,
    "vineyard":"santa barbara",
    "vintage":2011,
    "wineUnitIdentifiers":"wineunit.restaurant.strega-waterfront.1marinaparkdrive.wine.brand.etudelyric.varietal.pinotnoir.2011.glass",
    "brand":[{
    "about":"",
    "identifier":"brand.etudelyric",
    "deletedEntity":"",
    "lastUpdated":"2013-12-05 00:17:54 +0000",
    "name":"etude lyric",
    "version":1,
    "website":"",
    "wineIdentifiers":"",
    "wines":""
  }],
    "tastingNotes":"",
    "varietals":"",
    "wineUnits":""
  }]
  },
  {
    "flightIdentifiers":"",
    "groupIdentifiers":"",
    "identifier":"wineunit.restaurant.strega-waterfront.1marinaparkdrive.wine.brand.spellbound.varietal.merlot.2009.glass",
    "deletedEntity":"",
    "lastUpdated":"2013-12-05 00:17:54 +0000",
    "price":9,
    "quantity":"glass",
    "restaurantIdentifier":"restaurant.strega-waterfront.1marinaparkdrive",
    "version":1,
    "wineIdentifier":"wine.brand.spellbound.varietal.merlot.2009",
    "flights":"",
    "groups":"",
    "wine":[{
    "alcoholPercentage":3.8,
    "brandIdentifier":"brand.spellbound",
    "color":"red",
    "country":"united states of america",
    "dessert":"0",
    "identifier":"wine.brand.spellbound.varietal.merlot.2009",
    "deletedEntity":"",
    "lastUpdated":"2013-12-05 00:17:54 +0000",
    "name":"",
    "region":"",
    "sparkling":"0",
    "state":"california",
    "tastingNoteIdentifiers":"tastingnote.liquorice",
    "varietalIdentifiers":"varietal.merlot",
    "version":1,
    "vineyard":"lodi",
    "vintage":2009,
    "wineUnitIdentifiers":"wineunit.restaurant.strega-waterfront.1marinaparkdrive.wine.brand.spellbound.varietal.merlot.2009.glass",
    "brand":[{
    "about":"",
    "identifier":"brand.spellbound",
    "deletedEntity":"",
    "lastUpdated":"2013-12-05 00:17:54 +0000",
    "name":"spellbound",
    "version":1,
    "website":"",
    "wineIdentifiers":"",
    "wines":""
  }],
    "tastingNotes":"",
    "varietals":"",
    "wineUnits":""
  }]
  },
  {
    "flightIdentifiers":"",
    "groupIdentifiers":"",
    "identifier":"wineunit.restaurant.strega-waterfront.1marinaparkdrive.wine.brand.pauldolan.varietal.zinfandel.2010.glass",
    "deletedEntity":"",
    "lastUpdated":"2013-12-05 00:17:54 +0000",
    "price":10,
    "quantity":"glass",
    "restaurantIdentifier":"restaurant.strega-waterfront.1marinaparkdrive",
    "version":1,
    "wineIdentifier":"wine.brand.pauldolan.varietal.zinfandel.2010",
    "flights":"",
    "groups":"",
    "wine":[{
    "alcoholPercentage":3.2,
    "brandIdentifier":"brand.pauldolan",
    "color":"red",
    "country":"united states of america",
    "dessert":"0",
    "identifier":"wine.brand.pauldolan.varietal.zinfandel.2010",
    "deletedEntity":"",
    "lastUpdated":"2013-12-05 00:17:54 +0000",
    "name":"",
    "region":"",
    "sparkling":"0",
    "state":"california",
    "tastingNoteIdentifiers":"tastingnote.melon",
    "varietalIdentifiers":"varietal.zinfandel",
    "version":1,
    "vineyard":"mendocino county",
    "vintage":2010,
    "wineUnitIdentifiers":"wineunit.restaurant.strega-waterfront.1marinaparkdrive.wine.brand.pauldolan.varietal.zinfandel.2010.glass",
    "brand":[{
    "about":"",
    "identifier":"brand.pauldolan",
    "deletedEntity":"",
    "lastUpdated":"2013-12-05 00:17:54 +0000",
    "name":"paul dolan",
    "version":1,
    "website":"",
    "wineIdentifiers":"",
    "wines":""
  }],
    "tastingNotes":"",
    "varietals":"",
    "wineUnits":""
  }]
  },
  {
    "flightIdentifiers":"",
    "groupIdentifiers":"",
    "identifier":"wineunit.restaurant.strega-waterfront.1marinaparkdrive.wine.brand.alamos.varietal.malbec.2011.glass",
    "deletedEntity":"",
    "lastUpdated":"2013-12-05 00:17:54 +0000",
    "price":9,
    "quantity":"glass",
    "restaurantIdentifier":"restaurant.strega-waterfront.1marinaparkdrive",
    "version":1,
    "wineIdentifier":"wine.brand.alamos.varietal.malbec.2011",
    "flights":"",
    "groups":"",
    "wine":[{
    "alcoholPercentage":4.1,
    "brandIdentifier":"brand.alamos",
    "color":"red",
    "country":"argentina",
    "dessert":"0",
    "identifier":"wine.brand.alamos.varietal.malbec.2011",
    "deletedEntity":"",
    "lastUpdated":"2013-12-05 00:17:54 +0000",
    "name":"",
    "region":"mendoza",
    "sparkling":"0",
    "state":"",
    "tastingNoteIdentifiers":"tastingnote.minerals",
    "varietalIdentifiers":"varietal.malbec",
    "version":1,
    "vineyard":"mendoza",
    "vintage":2011,
    "wineUnitIdentifiers":"wineunit.restaurant.strega-waterfront.1marinaparkdrive.wine.brand.alamos.varietal.malbec.2011.glass",
    "brand":[{
    "about":"",
    "identifier":"brand.alamos",
    "deletedEntity":"",
    "lastUpdated":"2013-12-05 00:17:54 +0000",
    "name":"alamos",
    "version":1,
    "website":"",
    "wineIdentifiers":"",
    "wines":""
  }],
    "tastingNotes":"",
    "varietals":"",
    "wineUnits":""
  }]
  },
  {
    "flightIdentifiers":"",
    "groupIdentifiers":"",
    "identifier":"wineunit.restaurant.strega-waterfront.1marinaparkdrive.wine.brand.benziger.varietal.syrah.2007.glass",
    "deletedEntity":"",
    "lastUpdated":"2013-12-05 00:17:54 +0000",
    "price":12,
    "quantity":"glass",
    "restaurantIdentifier":"restaurant.strega-waterfront.1marinaparkdrive",
    "version":1,
    "wineIdentifier":"wine.brand.benziger.varietal.syrah.2007",
    "flights":"",
    "groups":"",
    "wine":[{
    "alcoholPercentage":4.4,
    "brandIdentifier":"brand.benziger",
    "color":"red",
    "country":"united states of america",
    "dessert":"0",
    "identifier":"wine.brand.benziger.varietal.syrah.2007",
    "deletedEntity":"",
    "lastUpdated":"2013-12-05 00:17:54 +0000",
    "name":"",
    "region":"",
    "sparkling":"0",
    "state":"california",
    "tastingNoteIdentifiers":"tastingnote.mint",
    "varietalIdentifiers":"varietal.syrah",
    "version":1,
    "vineyard":"sonoma",
    "vintage":2007,
    "wineUnitIdentifiers":"wineunit.restaurant.strega-waterfront.1marinaparkdrive.wine.brand.benziger.varietal.syrah.2007.glass",
    "brand":[{
    "about":"",
    "identifier":"brand.benziger",
    "deletedEntity":"",
    "lastUpdated":"2013-12-05 00:17:54 +0000",
    "name":"benziger",
    "version":1,
    "website":"",
    "wineIdentifiers":"",
    "wines":""
  }],
    "tastingNotes":"",
    "varietals":"",
    "wineUnits":""
  }]
  },
  {
    "flightIdentifiers":"",
    "groupIdentifiers":"",
    "identifier":"wineunit.restaurant.strega-waterfront.1marinaparkdrive.wine.brand.penfoldskoonungahills.varietal.shiraz.2010.glass",
    "deletedEntity":"",
    "lastUpdated":"2013-12-05 00:17:54 +0000",
    "price":9,
    "quantity":"glass",
    "restaurantIdentifier":"restaurant.strega-waterfront.1marinaparkdrive",
    "version":1,
    "wineIdentifier":"wine.brand.penfoldskoonungahills.varietal.shiraz.2010",
    "flights":"",
    "groups":"",
    "wine":[{
    "alcoholPercentage":3.7,
    "brandIdentifier":"brand.penfoldskoonungahills",
    "color":"red",
    "country":"australia",
    "dessert":"0",
    "identifier":"wine.brand.penfoldskoonungahills.varietal.shiraz.2010",
    "deletedEntity":"",
    "lastUpdated":"2013-12-05 00:17:54 +0000",
    "name":"",
    "region":"rawson",
    "sparkling":"0",
    "state":"",
    "tastingNoteIdentifiers":"tastingnote.nutmeg",
    "varietalIdentifiers":"varietal.shiraz",
    "version":1,
    "vineyard":"rawson",
    "vintage":2010,
    "wineUnitIdentifiers":"wineunit.restaurant.strega-waterfront.1marinaparkdrive.wine.brand.penfoldskoonungahills.varietal.shiraz.2010.glass",
    "brand":[{
    "about":"",
    "identifier":"brand.penfoldskoonungahills",
    "deletedEntity":"",
    "lastUpdated":"2013-12-05 00:17:54 +0000",
    "name":"penfolds koonunga hills",
    "version":1,
    "website":"",
    "wineIdentifiers":"",
    "wines":""
  }],
    "tastingNotes":"",
    "varietals":"",
    "wineUnits":""
  }]
  }
]
  }
]